{"authorDailyContributionsMap":{"flljy940":[],"nicolaskjh":[],"izniy":[],"bipplane":[]},"authorFileTypeContributionMap":{"flljy940":{"docs":0,"functional-code":0,"test-code":0},"nicolaskjh":{"docs":0,"functional-code":0,"test-code":0},"izniy":{"docs":0,"functional-code":0,"test-code":0},"bipplane":{"docs":0,"functional-code":0,"test-code":0}},"authorContributionVariance":{"flljy940":0.0,"nicolaskjh":0.0,"izniy":0.0,"bipplane":0.0},"authorDisplayNameMap":{"flljy940":"CS2103T-T16-4 JOSE..G YI","nicolaskjh":"CS2103T-T16-4 KOH ..OLAS","izniy":"CS2103T-T16-4 NG Y..N ZI","bipplane":"CS2103T-T16-4 RYAN..YANG"}}
