{"authorDailyContributionsMap":{"Masunori":[],"junngithub":[],"kevinlimantoro123":[{"date":"2025-04-06","commitResults":[{"hash":"55e2ecea1f8bdcf622afc5ecf92e41a756212f44","isMergeCommit":false,"messageTitle":"Fix bugs","messageBody":"","fileTypesAndContributionMap":{"functional-code":{"insertions":5,"deletions":3},"docs":{"insertions":13,"deletions":13},"test-code":{"insertions":2,"deletions":1}}},{"hash":"c61122f20029c9029638d74223ea62301cf7d53c","isMergeCommit":false,"messageTitle":"Fix checkstyle","messageBody":"","fileTypesAndContributionMap":{"functional-code":{"insertions":0,"deletions":1}}},{"hash":"7a0c85701be34d7dcc5593881f6c4feae86e68ef","isMergeCommit":true,"messageTitle":"Merge pull request #179 from kevinlimantoro123/fix-bugs","messageBody":"Fix bugs","fileTypesAndContributionMap":{}}]}],"NhatMinh0208":[]},"authorFileTypeContributionMap":{"Masunori":{"docs":0,"functional-code":0,"test-code":0},"junngithub":{"docs":0,"functional-code":0,"test-code":0},"kevinlimantoro123":{"docs":13,"functional-code":4,"test-code":2},"NhatMinh0208":{"docs":0,"functional-code":0,"test-code":0}},"authorContributionVariance":{"Masunori":0.0,"junngithub":0.0,"kevinlimantoro123":361.0,"NhatMinh0208":0.0},"authorDisplayNameMap":{"Masunori":"CS2103T-W13-4 DUON.. DUC","junngithub":"CS2103T-W13-4 NGOO.. SEN","kevinlimantoro123":"CS2103T-W13-4 KEVI..TORO","NhatMinh0208":"CS2103T-W13-4 NGUY..MINH"}}
