{"authorDailyContributionsMap":{"wenruu":[],"alexandtheoh":[],"angjozee":[],"nanditaselvaraju":[],"zechary28":[]},"authorFileTypeContributionMap":{"wenruu":{"docs":0,"functional-code":0,"test-code":0},"alexandtheoh":{"docs":0,"functional-code":0,"test-code":0},"angjozee":{"docs":0,"functional-code":0,"test-code":0},"nanditaselvaraju":{"docs":0,"functional-code":0,"test-code":0},"zechary28":{"docs":0,"functional-code":0,"test-code":0}},"authorContributionVariance":{"wenruu":0.0,"alexandtheoh":0.0,"angjozee":0.0,"nanditaselvaraju":0.0,"zechary28":0.0},"authorDisplayNameMap":{"wenruu":"CS2103T-T14-2 ZHAO..NRUI","alexandtheoh":"CS2103T-T14-2 OH Z..NDER","angjozee":"CS2103T-T14-2 ANG .. ZEE","nanditaselvaraju":"CS2103T-T14-2 SELV..DITA","zechary28":"CS2103T-T14-2 CHUA..HARY"}}
