{"authorDailyContributionsMap":{"nathtiekk":[{"date":"2025-04-07","commitResults":[{"hash":"737976de56db7588d497c3fba1c6d8fb51f5c210","isMergeCommit":false,"messageTitle":"Fixes #249","messageBody":"","fileTypesAndContributionMap":{"functional-code":{"insertions":0,"deletions":2}}},{"hash":"cb4cc86f2e596712aff49d99c872a99f73b4f601","isMergeCommit":false,"messageTitle":"Fix issues #206, #213, #219, #249","messageBody":"","fileTypesAndContributionMap":{"functional-code":{"insertions":3,"deletions":3},"test-code":{"insertions":2,"deletions":2}}},{"hash":"6c19ff28b460583f86f38be924fb946292b839ee","isMergeCommit":false,"messageTitle":"Fix duplicate prefix in filter command","messageBody":"","fileTypesAndContributionMap":{"functional-code":{"insertions":2,"deletions":0}}},{"hash":"93cbd0c73a466d065ab3e9fd30c21ff40c5907be","isMergeCommit":false,"messageTitle":"Fix #218 #199","messageBody":"","fileTypesAndContributionMap":{"functional-code":{"insertions":3,"deletions":1},"docs":{"insertions":3,"deletions":3}}},{"hash":"f56747eb219bcf73ba5c225a1427237460037d2e","isMergeCommit":false,"messageTitle":"Enhance FilterDateCommandParserTest","messageBody":"","fileTypesAndContributionMap":{"functional-code":{"insertions":4,"deletions":4},"test-code":{"insertions":30,"deletions":9}}},{"hash":"8ebaaf73b981e99d8a156bf20fd81feed6030072","isMergeCommit":true,"messageTitle":"Merge pull request #281 from nathtiekk/filter-bugs-1.5","messageBody":"Bugs in filter command v1.5","fileTypesAndContributionMap":{}},{"hash":"774c794618be5e72e30c772c05b3c8cc9b3c752b","isMergeCommit":false,"messageTitle":"Add Design considerations for Filter Command","messageBody":"","fileTypesAndContributionMap":{"docs":{"insertions":22,"deletions":1}}},{"hash":"148e8e55eaf86239f4015ff5e71e28c1c7941a1c","isMergeCommit":false,"messageTitle":"Standardize class diagram","messageBody":"","fileTypesAndContributionMap":{"docs":{"insertions":7,"deletions":5}}},{"hash":"bdd05590f9e80c0d0ad48b7fead7ebde0b16c6ca","isMergeCommit":true,"messageTitle":"Merge pull request #286 from nathtiekk/update-dev-guide","messageBody":"Add Design considerations for Filter Command in the Developers Guide","fileTypesAndContributionMap":{}},{"hash":"cd63b0402447a4a926d745d18ff77c921c75c4a9","isMergeCommit":false,"messageTitle":"Modify FilterDateCommandParserTest userInput","messageBody":"","fileTypesAndContributionMap":{"test-code":{"insertions":15,"deletions":15}}}]},{"date":"2025-04-08","commitResults":[{"hash":"3f62c800d5fc907b192f152d7ab0ce45ddffa184","isMergeCommit":false,"messageTitle":"Fix Manual Testing instructions for Viewing policy renewals in date range","messageBody":"","fileTypesAndContributionMap":{"docs":{"insertions":4,"deletions":4}}},{"hash":"2cd8ae3c6e22712912cc301aa7814c06013f9d2b","isMergeCommit":false,"messageTitle":"Adjust Class Diagram size and Manual Testing instructions","messageBody":"","fileTypesAndContributionMap":{"docs":{"insertions":1,"deletions":0}}},{"hash":"78b7fd17011254d63cab6e098a76e781e9229e65","isMergeCommit":false,"messageTitle":"Revert \"Fix Manual Testing instructions for Viewing policy renewals in date range\"","messageBody":"This reverts commit 3f62c800d5fc907b192f152d7ab0ce45ddffa184.\n","fileTypesAndContributionMap":{"docs":{"insertions":4,"deletions":4}}},{"hash":"d8e5dde848ace350c09db4de69b3b9512fb86aca","isMergeCommit":true,"messageTitle":"Merge pull request #321 from nathtiekk/pre1.6-fix","messageBody":"Pre1.6 fix for class diagram size and manual testing instructions","fileTypesAndContributionMap":{}},{"hash":"023677d4c02f4368181663418f9adce954b7a70e","isMergeCommit":true,"messageTitle":"Merge branch \u0027master\u0027 of https://github.com/nathtiekk/tp","messageBody":"","fileTypesAndContributionMap":{}},{"hash":"94c4bd94211e05b8f391f0f346d3272d287cff63","isMergeCommit":false,"messageTitle":"Resize class diagram","messageBody":"","fileTypesAndContributionMap":{"docs":{"insertions":1,"deletions":2}}},{"hash":"49df14bbdcb8ef4c7c36008aa266dea59bbceb2a","isMergeCommit":false,"messageTitle":"Fix unintended changes to manual testing instructions","messageBody":"","fileTypesAndContributionMap":{"docs":{"insertions":4,"deletions":4}}}]}],"yuyang011":[{"date":"2025-04-05","commitResults":[{"hash":"f2abfc2297ff35392d12ee4edfc5e0343a705231","isMergeCommit":false,"messageTitle":"Update addressbook.jar to InsureBook.jar","messageBody":"","fileTypesAndContributionMap":{"docs":{"insertions":1,"deletions":1}}},{"hash":"13350e915c784975a15cc53d78fe890b72ee4ce8","isMergeCommit":true,"messageTitle":"Merge pull request #217 from yuyang011/branch-fix-jar-name","messageBody":"","fileTypesAndContributionMap":{}}]},{"date":"2025-04-06","commitResults":[{"hash":"75dfe87aa5ffcd74344c7ad574962bccca4629e6","isMergeCommit":false,"messageTitle":"Update UML diagram with PolicyType and RenewalDate","messageBody":"","fileTypesAndContributionMap":{"docs":{"insertions":8,"deletions":0}}},{"hash":"7e154807cd1bc6cf88bf3c97dab12547b8b03e4a","isMergeCommit":false,"messageTitle":"Update font size","messageBody":"","fileTypesAndContributionMap":{"docs":{"insertions":2,"deletions":0}}},{"hash":"44ac6c77eda9a923e8035e53c56b9761fbc3115a","isMergeCommit":true,"messageTitle":"Merge pull request #276 from yuyang011/branch-update-model","messageBody":"","fileTypesAndContributionMap":{}}]},{"date":"2025-04-07","commitResults":[{"hash":"b9da3ea0704f4d2411a7fb1c8dce607ec3403d52","isMergeCommit":false,"messageTitle":"Update viewrenewals to refresh after editing","messageBody":"","fileTypesAndContributionMap":{"functional-code":{"insertions":7,"deletions":3}}},{"hash":"0bbd0943096a2ea58e2d900ffac50520d5ab3b75","isMergeCommit":false,"messageTitle":"Fix checkstyle","messageBody":"","fileTypesAndContributionMap":{"functional-code":{"insertions":0,"deletions":1}}},{"hash":"02fe6e6f45e8e90e25e38dc91df24d39c88f01dd","isMergeCommit":false,"messageTitle":"Add manual testing","messageBody":"","fileTypesAndContributionMap":{"docs":{"insertions":169,"deletions":4}}},{"hash":"5d4c8b9bd3a220d9634a3ff3e955141ef11eab39","isMergeCommit":false,"messageTitle":"Update to fix manual test","messageBody":"","fileTypesAndContributionMap":{"docs":{"insertions":17,"deletions":10}}},{"hash":"c70ea59eaddbd228ac375258353e18c5ac806a96","isMergeCommit":true,"messageTitle":"Merge pull request #282 from yuyang011/branch-manual-testing","messageBody":"","fileTypesAndContributionMap":{}},{"hash":"a8cfee766350af122df30e963e4d80ec1ac1b98b","isMergeCommit":true,"messageTitle":"Merge pull request #280 from yuyang011/branch-fix-update-renewal","messageBody":"","fileTypesAndContributionMap":{}},{"hash":"e65dd0e3a1032d3173e0ea28d266d3cf12d17228","isMergeCommit":false,"messageTitle":"Update manual testing","messageBody":"","fileTypesAndContributionMap":{"docs":{"insertions":9,"deletions":9}}},{"hash":"0aa45ab19610cadb546a72efbfc6a3d071b32ac2","isMergeCommit":false,"messageTitle":"Update commands with screenshots","messageBody":"","fileTypesAndContributionMap":{"docs":{"insertions":6,"deletions":0}}},{"hash":"bca0d31abe2264fe06dd94ffa2ab22066e0ca68f","isMergeCommit":true,"messageTitle":"Merge pull request #293 from yuyang011/branch-expected-outcome","messageBody":"","fileTypesAndContributionMap":{}},{"hash":"b668f84846aef8abe60fe6306c3fe25ebbda0493","isMergeCommit":true,"messageTitle":"Merge pull request #290 from yuyang011/branch-update-manual","messageBody":"","fileTypesAndContributionMap":{}},{"hash":"fa8a8dd5d302dc5a4b68dd14048ba7153c6c8ab9","isMergeCommit":true,"messageTitle":"Merge pull request #296 from yuyang011/branch-expected-outcome","messageBody":"","fileTypesAndContributionMap":{}},{"hash":"6f643aa7698d08ff0b8fbeaa99e4e431e37fe4ce","isMergeCommit":false,"messageTitle":"Update manual testing","messageBody":"","fileTypesAndContributionMap":{"docs":{"insertions":11,"deletions":11}}},{"hash":"4b7b5d4ad9714aa9dd3f617ab3ac4c962b5e9d6d","isMergeCommit":true,"messageTitle":"Merge pull request #298 from yuyang011/branch-update-testing","messageBody":"","fileTypesAndContributionMap":{}}]},{"date":"2025-04-08","commitResults":[{"hash":"f6bf1483e3ef2716ab0b5b423750eb3ffe08e9cd","isMergeCommit":false,"messageTitle":"Update partial search documentation","messageBody":"","fileTypesAndContributionMap":{"docs":{"insertions":2,"deletions":0}}},{"hash":"2008485df0dd6c84358848acda720723c6a44039","isMergeCommit":false,"messageTitle":"Update typo","messageBody":"","fileTypesAndContributionMap":{"docs":{"insertions":1,"deletions":1}}},{"hash":"d9fab98b025cadd3b4caab57bea9f1d46f2dd97f","isMergeCommit":true,"messageTitle":"Merge pull request #320 from yuyang011/branch-bug-fix","messageBody":"","fileTypesAndContributionMap":{}},{"hash":"87d6952317a2a4d9f4bc6aaad56e79f52431c5da","isMergeCommit":false,"messageTitle":"Update find command","messageBody":"","fileTypesAndContributionMap":{"docs":{"insertions":2,"deletions":1}}},{"hash":"82ba599c04aa64cf3828ca697acdc833d3a3b72f","isMergeCommit":true,"messageTitle":"Merge pull request #322 from yuyang011/branch-bug-fix","messageBody":"","fileTypesAndContributionMap":{}},{"hash":"e7d1a5a83fbb774f253ae0d32758ec4803a9f709","isMergeCommit":false,"messageTitle":"Update manual test","messageBody":"","fileTypesAndContributionMap":{"docs":{"insertions":1,"deletions":1}}},{"hash":"d78bad82715f9dd04840e1c5f4f0de6953d9135f","isMergeCommit":false,"messageTitle":"Update typos","messageBody":"","fileTypesAndContributionMap":{"docs":{"insertions":3,"deletions":3}}}]}],"Jovin-Ang":[{"date":"2025-04-05","commitResults":[{"hash":"3a85156bd6b270f0772083ed158089b0148c2d50","isMergeCommit":false,"messageTitle":"Fix markdown rendering on info box","messageBody":"","fileTypesAndContributionMap":{"docs":{"insertions":1,"deletions":0}}}]},{"date":"2025-04-06","commitResults":[{"hash":"4121377cc312a729452b15ebcebb5a739a20535e","isMergeCommit":true,"messageTitle":"Merge pull request #265 from yuyang011/branch-fix-jar-name","messageBody":"Update addressbook.jar to InsureBook.jar","fileTypesAndContributionMap":{}},{"hash":"349e66560c520015db7fd350ca4e05c871594759","isMergeCommit":false,"messageTitle":"Enforce single usage of SORT_ORDER prefix in find command","messageBody":"","fileTypesAndContributionMap":{"functional-code":{"insertions":2,"deletions":0},"docs":{"insertions":4,"deletions":4},"test-code":{"insertions":7,"deletions":0}}},{"hash":"779eccea6bb729d341330925d512b0dd9b524896","isMergeCommit":false,"messageTitle":"Prevent invalid PolicyType in Find command","messageBody":"* Utilise parsePolicyTypes method in FindCommandParser\n* Refactor PolicyTypeContainsKeywordsPredicate to use PolicyType\ninstead of String\n* Update test cases\n","fileTypesAndContributionMap":{"functional-code":{"insertions":3,"deletions":9},"test-code":{"insertions":10,"deletions":13}}},{"hash":"4d1bcc4796ed8430c181c19a08452c3a18d28f22","isMergeCommit":true,"messageTitle":"Merge pull request #267 from Jovin-Ang/add-sort-find","messageBody":"Find command bug fixes","fileTypesAndContributionMap":{}}]},{"date":"2025-04-07","commitResults":[{"hash":"c2bedb45066bc198ff3a0a4d8fef79aa1c94292f","isMergeCommit":false,"messageTitle":"Add design consideration to filter in DG","messageBody":"","fileTypesAndContributionMap":{"docs":{"insertions":30,"deletions":8}}},{"hash":"458798bc4e8a0a6235d0d04ca89d3c2441a7fdf7","isMergeCommit":true,"messageTitle":"Merge branch \u0027master\u0027 into update-docs","messageBody":"","fileTypesAndContributionMap":{}},{"hash":"0825c5655ae9934a3747f5af2a46f9e01defdb9a","isMergeCommit":true,"messageTitle":"Merge branch \u0027master\u0027 into update-docs","messageBody":"","fileTypesAndContributionMap":{}},{"hash":"46034561b4f9eb6b8de311d4cc250e92d991663a","isMergeCommit":false,"messageTitle":"Update User Guide with examples and expected outputs for find command","messageBody":"","fileTypesAndContributionMap":{"docs":{"insertions":15,"deletions":1}}},{"hash":"ee34999e2826a2aaa888102025447ea6fd573faf","isMergeCommit":true,"messageTitle":"Merge pull request #297 from Jovin-Ang/update-docs","messageBody":"Add visual examples of find command to UG","fileTypesAndContributionMap":{}},{"hash":"adfa5bb99c0190fa107e4fe90bc6d6eed65292b1","isMergeCommit":false,"messageTitle":"Update User Guide","messageBody":"","fileTypesAndContributionMap":{"docs":{"insertions":1,"deletions":1}}}]},{"date":"2025-04-08","commitResults":[{"hash":"b0912a9a61a218ae279cdd95701c6bd881bd440e","isMergeCommit":false,"messageTitle":"Specify sorting options in User Guide","messageBody":"","fileTypesAndContributionMap":{"docs":{"insertions":15,"deletions":7}}},{"hash":"f16801f7734469a2315ab9d2910ecf65f07ea0db","isMergeCommit":true,"messageTitle":"Merge branch \u0027master\u0027 into update-docs","messageBody":"","fileTypesAndContributionMap":{}},{"hash":"1f95a36998879685658b3462d7866eb3feee6a25","isMergeCommit":false,"messageTitle":"Remove placeholder text from Developer Guide","messageBody":"","fileTypesAndContributionMap":{"docs":{"insertions":0,"deletions":3}}},{"hash":"20caf88366772574f3f5a667b4cf46536ddb2e76","isMergeCommit":false,"messageTitle":"Clarify field rules in User Guide for find command","messageBody":"","fileTypesAndContributionMap":{"docs":{"insertions":1,"deletions":0}}},{"hash":"14bd0cb6f0107165a8d88478ee2cbc0481007e36","isMergeCommit":true,"messageTitle":"Merge pull request #328 from Jovin-Ang/update-docs","messageBody":"Specify sorting options in User Guide","fileTypesAndContributionMap":{}}]}],"MakiseKurisuX":[{"date":"2025-04-06","commitResults":[{"hash":"0ef6e23e39788002d81ca40f39378a4dd30f8412","isMergeCommit":false,"messageTitle":"Fix Bugs found during PE-D","messageBody":"","fileTypesAndContributionMap":{"functional-code":{"insertions":8,"deletions":3},"docs":{"insertions":43,"deletions":28},"test-code":{"insertions":3,"deletions":2}}},{"hash":"fd76f9b81804c07634c6f3d6cf06aff7412bf0c3","isMergeCommit":false,"messageTitle":"Update UserGuide.md","messageBody":"","fileTypesAndContributionMap":{"docs":{"insertions":2,"deletions":0}}},{"hash":"27847d5542a7a6374105c6dca5c8c74a61391748","isMergeCommit":true,"messageTitle":"Merge pull request #269 from MakiseKurisuX/branch-bugfixes3","messageBody":"Fix Various Bugs Found in PE-D","fileTypesAndContributionMap":{}},{"hash":"6815c65666fc3629c7eddbf513b2381bac23b407","isMergeCommit":false,"messageTitle":"Bug Fixes for PE-D bugs","messageBody":"","fileTypesAndContributionMap":{"functional-code":{"insertions":24,"deletions":11},"docs":{"insertions":3,"deletions":7}}},{"hash":"e3032ce0d22bffb6fb6f50927441f1a4ff7be821","isMergeCommit":false,"messageTitle":"Update AddCommandParser.java","messageBody":"","fileTypesAndContributionMap":{"functional-code":{"insertions":1,"deletions":1}}},{"hash":"d5826f6b9c1e7da8067966faf121411756a8ab99","isMergeCommit":true,"messageTitle":"Merge pull request #274 from MakiseKurisuX/branch-bugfixes4","messageBody":"Fix Various Bugs found in PE-D","fileTypesAndContributionMap":{}}]},{"date":"2025-04-07","commitResults":[{"hash":"1dd9ac1a702812c00a6771dd0d36681f12c73765","isMergeCommit":false,"messageTitle":"Fix Bugs Highlighted in PE-D","messageBody":"","fileTypesAndContributionMap":{"functional-code":{"insertions":21,"deletions":25},"docs":{"insertions":17,"deletions":6},"test-code":{"insertions":41,"deletions":29}}},{"hash":"3c35493d5f742951187c683c28926713b243cf03","isMergeCommit":false,"messageTitle":"Update DeveloperGuide.md","messageBody":"","fileTypesAndContributionMap":{"docs":{"insertions":0,"deletions":8}}},{"hash":"541d5825b9f7ac1232ea383c87a0cf84e2ffdd71","isMergeCommit":true,"messageTitle":"Merge pull request #278 from MakiseKurisuX/branch-bugfixes5","messageBody":"Fix Bugs Highlighted in PE-D","fileTypesAndContributionMap":{}},{"hash":"9229bbd702b1de1be38411febeaa30c7b731c2be","isMergeCommit":false,"messageTitle":"Update DeveloperGuide.md","messageBody":"","fileTypesAndContributionMap":{"docs":{"insertions":96,"deletions":40}}},{"hash":"05b8b8fad0ed2d63be152ea4983fadb3c846ff13","isMergeCommit":false,"messageTitle":"Update DeveloperGuide.md","messageBody":"","fileTypesAndContributionMap":{"docs":{"insertions":7,"deletions":7}}},{"hash":"22b4e215255959907247c0c0c6d15a96164a1356","isMergeCommit":false,"messageTitle":"Update DG and UG","messageBody":"","fileTypesAndContributionMap":{"docs":{"insertions":23,"deletions":1}}},{"hash":"bdc887efe8f6f19ed3233a3b8bcac40c82bccde7","isMergeCommit":true,"messageTitle":"Merge branch \u0027master\u0027 into branch-ugdg1","messageBody":"","fileTypesAndContributionMap":{}},{"hash":"cc43d6eac286de15e5034be36c5d9650737651b4","isMergeCommit":true,"messageTitle":"Merge pull request #283 from MakiseKurisuX/branch-ugdg1","messageBody":"Add Use Cases and Update Glossary","fileTypesAndContributionMap":{}},{"hash":"307cb54f0a046cef65b118b5f9766b796461330e","isMergeCommit":false,"messageTitle":"Update UserGuide.md","messageBody":"","fileTypesAndContributionMap":{"docs":{"insertions":16,"deletions":16}}},{"hash":"72ace62b4c9aafd7fcbf5b31b7e9a69e33eab76f","isMergeCommit":false,"messageTitle":"Update UserGuide","messageBody":"","fileTypesAndContributionMap":{"docs":{"insertions":22,"deletions":0}}},{"hash":"4eb4cc38e52525196973383d29fdbd53276430fd","isMergeCommit":false,"messageTitle":"Update AddCommand.java","messageBody":"","fileTypesAndContributionMap":{"functional-code":{"insertions":1,"deletions":1}}},{"hash":"ab650a9c0fc8e1231629e36a65e48c7acd1a9201","isMergeCommit":true,"messageTitle":"Merge branch \u0027master\u0027 into branch-ugdg2","messageBody":"","fileTypesAndContributionMap":{}},{"hash":"bf0494d4c9f35be5eb334424771be3b92ef8554b","isMergeCommit":true,"messageTitle":"Merge pull request #294 from MakiseKurisuX/branch-updateug","messageBody":"Add Images to User Guide and Update Sample","fileTypesAndContributionMap":{}},{"hash":"cc94e75f3d050864182f4d6385fe3289664fa15e","isMergeCommit":true,"messageTitle":"Merge pull request #289 from MakiseKurisuX/branch-ugdg2","messageBody":"Update DG and UG","fileTypesAndContributionMap":{}}]},{"date":"2025-04-08","commitResults":[{"hash":"a4d779bd350d5423a5e1b5ebf2ae7388d83834a0","isMergeCommit":false,"messageTitle":"Fix Bugs found in Prelim Test","messageBody":"","fileTypesAndContributionMap":{"docs":{"insertions":15,"deletions":25}}},{"hash":"a8ce05491510df7de950469cd6174ae03c7d3fc1","isMergeCommit":true,"messageTitle":"Merge pull request #318 from MakiseKurisuX/branch-bugfixes7","messageBody":"Fix Bugs found in Prelim Test","fileTypesAndContributionMap":{}},{"hash":"79089df4c161852655b8008991e63dd43491e8bf","isMergeCommit":false,"messageTitle":"Fix Bugs Found in Prelim Test 2","messageBody":"","fileTypesAndContributionMap":{"docs":{"insertions":54,"deletions":53}}},{"hash":"6d440eff22667f8cd75c21d43896c5664d9e6b1e","isMergeCommit":true,"messageTitle":"Merge pull request #302 from Jovin-Ang/update-docs","messageBody":"Update User Guide","fileTypesAndContributionMap":{}},{"hash":"3e5de2257532be2e70e63eca61725682f189328e","isMergeCommit":true,"messageTitle":"Merge pull request #324 from MakiseKurisuX/branch-bugfixes8","messageBody":"Fix Bugs Found in Prelim Test 2","fileTypesAndContributionMap":{}},{"hash":"0eb8ab6c29636fad36abe1e7491512d8c9ea2d01","isMergeCommit":false,"messageTitle":"Update AboutUs.md","messageBody":"","fileTypesAndContributionMap":{"docs":{"insertions":9,"deletions":9}}},{"hash":"4ac365fd550c7c8be8c270e777a94c984e73052e","isMergeCommit":true,"messageTitle":"Merge pull request #327 from MakiseKurisuX/branch-aboutusFinal","messageBody":"Update About Us","fileTypesAndContributionMap":{}},{"hash":"534f2d99459ef0f573d580789cd56c016c2ed21a","isMergeCommit":true,"messageTitle":"Merge pull request #325 from nathtiekk/resize-class-diagram","messageBody":"Resize class diagram","fileTypesAndContributionMap":{}},{"hash":"f8e9dd2fd59a2401a4119e26a5884c52330ab6aa","isMergeCommit":false,"messageTitle":"Update UserGuide.md","messageBody":"","fileTypesAndContributionMap":{"docs":{"insertions":0,"deletions":8}}},{"hash":"84b3943f2c0b354b9d386deceeb58d76519cf89e","isMergeCommit":false,"messageTitle":"Update UserGuide.md","messageBody":"","fileTypesAndContributionMap":{"docs":{"insertions":1,"deletions":3}}},{"hash":"4cbfb25363a488964b6bf9d1162dbb1684be2131","isMergeCommit":false,"messageTitle":"Update UserGuide.md","messageBody":"","fileTypesAndContributionMap":{"docs":{"insertions":0,"deletions":2}}},{"hash":"86c12aa477e7188940c60b53515904dd2318d001","isMergeCommit":true,"messageTitle":"Merge pull request #330 from AY2425S2-CS2103-F08-2/MakiseKurisuX-patch-1","messageBody":"Update UserGuide.md","fileTypesAndContributionMap":{}},{"hash":"9ca05a1aeaae5e541926d311990d8a6bb136f0d8","isMergeCommit":false,"messageTitle":"Update UserGuide.md","messageBody":"","fileTypesAndContributionMap":{"docs":{"insertions":1,"deletions":1}}},{"hash":"fc62a25ea33dc722bc0db302d87a6326c4fbb00a","isMergeCommit":true,"messageTitle":"Merge pull request #332 from yuyang011/branch-quick-fix","messageBody":"Update manual test","fileTypesAndContributionMap":{}}]}],"johngao122":[{"date":"2025-04-06","commitResults":[{"hash":"698a57ec2746982357edda18e760d2a7ee0173c7","isMergeCommit":false,"messageTitle":"Fix bug for issue 257","messageBody":"","fileTypesAndContributionMap":{"functional-code":{"insertions":2,"deletions":0},"test-code":{"insertions":17,"deletions":0}}},{"hash":"d85589b2accf259a3fcfce61c45d20a9a141dfc8","isMergeCommit":false,"messageTitle":"Fix bug for issue 215","messageBody":"","fileTypesAndContributionMap":{"functional-code":{"insertions":7,"deletions":8}}},{"hash":"9b59b39d016d1f73f38bd561f643a108574b532d","isMergeCommit":false,"messageTitle":"Fix bug for issue 210","messageBody":"","fileTypesAndContributionMap":{"functional-code":{"insertions":1,"deletions":1},"docs":{"insertions":3,"deletions":3}}},{"hash":"d64096997cbbc011930dca7be11e7bbb376d16d0","isMergeCommit":false,"messageTitle":"Fix bug for issue 211 and 201","messageBody":"","fileTypesAndContributionMap":{"functional-code":{"insertions":3,"deletions":3},"test-code":{"insertions":12,"deletions":7}}},{"hash":"3b709baba693532cbcaca2883a377f7712687d1c","isMergeCommit":false,"messageTitle":"Fix tests and checkstyle issues","messageBody":"","fileTypesAndContributionMap":{"functional-code":{"insertions":1,"deletions":4},"test-code":{"insertions":269,"deletions":117}}},{"hash":"67600954232165b28a1ea980fa7c9b6042d3b978","isMergeCommit":false,"messageTitle":"Fix tests and checkstyle issues","messageBody":"","fileTypesAndContributionMap":{"test-code":{"insertions":13,"deletions":1}}},{"hash":"514ef841e8bad2756e32ce8366440cbdc5abbff5","isMergeCommit":false,"messageTitle":"Fix tests and checkstyle issues","messageBody":"","fileTypesAndContributionMap":{"test-code":{"insertions":11,"deletions":7}}},{"hash":"fa0c63100e66ff0595637dca6f7488011967d89a","isMergeCommit":false,"messageTitle":"Fix tests and checkstyle issues","messageBody":"","fileTypesAndContributionMap":{"test-code":{"insertions":2,"deletions":2}}},{"hash":"0ae567d7ea2475372ea1d9d75ca25d020afdeb69","isMergeCommit":false,"messageTitle":"Fix code according to comments","messageBody":"","fileTypesAndContributionMap":{"functional-code":{"insertions":2,"deletions":1},"test-code":{"insertions":0,"deletions":14}}},{"hash":"435d808b6b7c95ddccd0c1e5429ad448ea280a76","isMergeCommit":false,"messageTitle":"Fix #205","messageBody":"","fileTypesAndContributionMap":{"functional-code":{"insertions":0,"deletions":1}}},{"hash":"923383266509dfb9c329dd27a415a03fec1b41f7","isMergeCommit":false,"messageTitle":"Fix #196","messageBody":"","fileTypesAndContributionMap":{"functional-code":{"insertions":9,"deletions":5}}},{"hash":"572b7f67f8e75bbce7db4edd208f83e75bc19a7e","isMergeCommit":false,"messageTitle":"Fix tests and checkstyle issues","messageBody":"","fileTypesAndContributionMap":{"functional-code":{"insertions":0,"deletions":2},"test-code":{"insertions":45,"deletions":79}}},{"hash":"08763d15f0a5f09e3ac7c45e3a9c8631900379a7","isMergeCommit":true,"messageTitle":"Merge pull request #271 from johngao122/branch-bug-fix-2","messageBody":"Branch bug fix 2","fileTypesAndContributionMap":{}},{"hash":"ff69e14d38a38813cd74aad99d4c480e00676b82","isMergeCommit":false,"messageTitle":"Add note on matchingpersons","messageBody":"","fileTypesAndContributionMap":{"functional-code":{"insertions":2,"deletions":0}}},{"hash":"86c565d06be7786f393e0ee5c7c514d900731464","isMergeCommit":true,"messageTitle":"Merge pull request #268 from johngao122/branch-bug-fix","messageBody":"Branch bug fix","fileTypesAndContributionMap":{}},{"hash":"302fa3ab138ca3a2cef8683a57bc54506624be5d","isMergeCommit":false,"messageTitle":"Rehaul user guide","messageBody":"","fileTypesAndContributionMap":{"docs":{"insertions":333,"deletions":148}}},{"hash":"3ec115b7043cd6d3b785593a9d94376a3a21c892","isMergeCommit":false,"messageTitle":"Redo layout of userguide","messageBody":"","fileTypesAndContributionMap":{"docs":{"insertions":85,"deletions":45}}},{"hash":"1d6c1f3caeae46bb4cc0b77b9defaf54be3da0c6","isMergeCommit":false,"messageTitle":"Fix checkstyle issues","messageBody":"","fileTypesAndContributionMap":{"docs":{"insertions":8,"deletions":14}}},{"hash":"976aea447c7bb8ed6663d7433eaa33ff23b67e80","isMergeCommit":false,"messageTitle":"Documentation fix","messageBody":"","fileTypesAndContributionMap":{"docs":{"insertions":7,"deletions":11}}},{"hash":"e0f29587bd28d4214e26a347a27a80a8706bcb77","isMergeCommit":true,"messageTitle":"Merge branch \u0027master\u0027 into ug-redo","messageBody":"","fileTypesAndContributionMap":{}},{"hash":"5c8ab1bcddee87854386a4375054d83ac6755276","isMergeCommit":true,"messageTitle":"Merge pull request #272 from johngao122/ug-redo","messageBody":"Ug redo","fileTypesAndContributionMap":{}}]},{"date":"2025-04-07","commitResults":[{"hash":"759db87d525b771cd7f29acb448faf2fc2c85d4a","isMergeCommit":false,"messageTitle":"Change duplicate condition for add and edit command","messageBody":"","fileTypesAndContributionMap":{"functional-code":{"insertions":72,"deletions":17},"docs":{"insertions":39,"deletions":14},"test-code":{"insertions":67,"deletions":12}}},{"hash":"b2d620e45bdb0a68143f2207758556e47b9039ec","isMergeCommit":false,"messageTitle":"Fix minor code issue","messageBody":"","fileTypesAndContributionMap":{"functional-code":{"insertions":1,"deletions":1}}},{"hash":"19aabca30be6f35cb93b6fe5f2b5ec3a12c36621","isMergeCommit":false,"messageTitle":"Fix minor code issue","messageBody":"","fileTypesAndContributionMap":{"functional-code":{"insertions":2,"deletions":3}}},{"hash":"4cc2b35900c345bf9443d66fe80ae171ac45383e","isMergeCommit":true,"messageTitle":"Merge pull request #277 from johngao122/duplicate-fix","messageBody":"","fileTypesAndContributionMap":{}},{"hash":"6fde5415683e64eb84fbd69d7fa867ddefe6aa51","isMergeCommit":false,"messageTitle":"Fix formatting for date format for filter command","messageBody":"","fileTypesAndContributionMap":{"functional-code":{"insertions":8,"deletions":5}}},{"hash":"56b0f73c28ecffa092109b65bdf688178625674b","isMergeCommit":false,"messageTitle":"Fix checkstyle issues","messageBody":"","fileTypesAndContributionMap":{"functional-code":{"insertions":2,"deletions":2},"test-code":{"insertions":9,"deletions":3}}},{"hash":"ad61bc9880521e85e1bdb7d223f148d52e2721f0","isMergeCommit":true,"messageTitle":"Merge pull request #285 from johngao122/filter-message-fix","messageBody":"Filter message fix","fileTypesAndContributionMap":{}},{"hash":"cdb8cecb459a3895550ae1f29befea048ce38f7a","isMergeCommit":false,"messageTitle":"Fix sequence diagrams for add, filter and renew","messageBody":"","fileTypesAndContributionMap":{"docs":{"insertions":6,"deletions":0}}},{"hash":"f2ea23acee3581179c93b9637e301ffd8bb1e6d3","isMergeCommit":false,"messageTitle":"Remove Tutorials section from site map","messageBody":"","fileTypesAndContributionMap":{"docs":{"insertions":1,"deletions":12}}},{"hash":"752fb7976f847e91870ced3b1859f106747ab674","isMergeCommit":true,"messageTitle":"Merge pull request #287 from johngao122/dg-fix","messageBody":"Fix sequence diagrams for add, filter and renew","fileTypesAndContributionMap":{}},{"hash":"ca122d874906fce1439460d89311932affbef11f","isMergeCommit":false,"messageTitle":"Add screenshots for policy management commands in user guide","messageBody":"","fileTypesAndContributionMap":{"docs":{"insertions":25,"deletions":1}}},{"hash":"e160d88a6fdcb0ff1874d8e6ea364330c7660818","isMergeCommit":true,"messageTitle":"Merge pull request #292 from johngao122/ug-visual","messageBody":"Add screenshots for policy management commands in user guide","fileTypesAndContributionMap":{}},{"hash":"dcd1b9c6e81fe525810d021b77df9114b1077f2a","isMergeCommit":true,"messageTitle":"Merge pull request #291 from Jovin-Ang/update-docs","messageBody":"Update some DG stuff","fileTypesAndContributionMap":{}},{"hash":"b823cce3768fc2b8a274047588070c381b9fc006","isMergeCommit":true,"messageTitle":"Merge pull request #295 from nathtiekk/fix-FilterDateCommandParserTest","messageBody":"Modify FilterDateCommandParserTest userInput","fileTypesAndContributionMap":{}}]},{"date":"2025-04-08","commitResults":[{"hash":"af2ea7aec2396da7aa4ab95fb4438adcefe29b2d","isMergeCommit":false,"messageTitle":"Fix issue #303","messageBody":"","fileTypesAndContributionMap":{"docs":{"insertions":0,"deletions":1}}},{"hash":"a24925f2aed2e3ccb44f03251756ee196518154a","isMergeCommit":false,"messageTitle":"Fix issue #307","messageBody":"","fileTypesAndContributionMap":{"docs":{"insertions":0,"deletions":1}}},{"hash":"5c6fffbe44cf8a9204c72c6f97974842376fd0f2","isMergeCommit":false,"messageTitle":"Fix issue #310","messageBody":"","fileTypesAndContributionMap":{"docs":{"insertions":10,"deletions":10}}},{"hash":"b027b7f93a074e837db96ae2a39baba1fdd343c9","isMergeCommit":false,"messageTitle":"Fix issue #312","messageBody":"","fileTypesAndContributionMap":{"docs":{"insertions":1,"deletions":1}}},{"hash":"18fa0bd0aa4ef8a7372cd66e5110956699bcb725","isMergeCommit":false,"messageTitle":"Fix issue #313","messageBody":"","fileTypesAndContributionMap":{"docs":{"insertions":0,"deletions":8}}},{"hash":"83e978aa5bbf4b591d3053bef785208d9636b0fa","isMergeCommit":false,"messageTitle":"Fix issue #314","messageBody":"","fileTypesAndContributionMap":{"docs":{"insertions":39,"deletions":3}}},{"hash":"dd616d5885ed38cf1bbda5510d10c9d58a9ec1dd","isMergeCommit":true,"messageTitle":"Merge pull request #319 from johngao122/final-bug-fixes","messageBody":"Final bug fixes","fileTypesAndContributionMap":{}},{"hash":"2567081459571fb6dec025ce3a8f7911d1d13780","isMergeCommit":false,"messageTitle":"Fix issue #316","messageBody":"","fileTypesAndContributionMap":{"docs":{"insertions":2,"deletions":2}}},{"hash":"18df0a62b5795675ef1d79e0bc74da75cc6d0b85","isMergeCommit":true,"messageTitle":"Merge pull request #326 from johngao122/hyperlink-fix","messageBody":"Fix issue #316","fileTypesAndContributionMap":{}},{"hash":"2ac76c8ee32ea706d6d9ac811b0c060a6a1fb21c","isMergeCommit":true,"messageTitle":"Merge pull request #329 from MakiseKurisuX/branch-bugfixes9","messageBody":"Fix UserGuide","fileTypesAndContributionMap":{}},{"hash":"506664a735a2a164e1e48eb4f2d0cc319374541b","isMergeCommit":true,"messageTitle":"Merge pull request #331 from MakiseKurisuX/branch-bugfixes10","messageBody":"Update UserGuide.md","fileTypesAndContributionMap":{}},{"hash":"60df7ee82596ae609c9b64ba11f405c53ddd6f6d","isMergeCommit":true,"messageTitle":"Merge pull request #333 from yuyang011/branch-quick-fix","messageBody":"Update typos","tags":["v1.6"],"fileTypesAndContributionMap":{}}]}]},"authorFileTypeContributionMap":{"nathtiekk":{"docs":35,"functional-code":11,"test-code":43},"yuyang011":{"docs":183,"functional-code":6,"test-code":0},"Jovin-Ang":{"docs":40,"functional-code":5,"test-code":17},"MakiseKurisuX":{"docs":199,"functional-code":49,"test-code":44},"johngao122":{"docs":393,"functional-code":92,"test-code":422}},"authorContributionVariance":{"nathtiekk":3139.0,"yuyang011":11553.5,"Jovin-Ang":490.1875,"MakiseKurisuX":18244.25,"johngao122":272626.7},"authorDisplayNameMap":{"nathtiekk":"CS2103-F08-2 KEIT.. TAN","yuyang011":"CS2103-F08-2 TAN ..YANG","Jovin-Ang":"CS2103-F08-2 JOVI..HENG","MakiseKurisuX":"CS2103-F08-2 TAN ..RVIN","johngao122":"CS2103-F08-2 JOHN..AHAO"}}
