{"authorDailyContributionsMap":{"Parrycys":[],"GCheeYang":[],"Inquisitivrx":[],"kea-S":[],"sherwinee":[]},"authorFileTypeContributionMap":{"Parrycys":{"docs":0,"functional-code":0,"test-code":0},"GCheeYang":{"docs":0,"functional-code":0,"test-code":0},"Inquisitivrx":{"docs":0,"functional-code":0,"test-code":0},"kea-S":{"docs":0,"functional-code":0,"test-code":0},"sherwinee":{"docs":0,"functional-code":0,"test-code":0}},"authorContributionVariance":{"Parrycys":0.0,"GCheeYang":0.0,"Inquisitivrx":0.0,"kea-S":0.0,"sherwinee":0.0},"authorDisplayNameMap":{"Parrycys":"CS2103-F09-3 PARR..HENG","GCheeYang":"CS2103-F09-3 GOH ..YANG","Inquisitivrx":"CS2103-F09-3 GALV..IANG","kea-S":"CS2103-F09-3 KEA ..ANTO","sherwinee":"CS2103-F09-3 SHER..N EE"}}
